{
	"RemapUnityFiles": 
	{
		"Module.AISentience.cpp.obj": [
			"AIHeard.cpp.obj",
			"AIInfoSharingComponent.cpp.obj",
			"AIInteractionAnimations.cpp.obj",
			"AISense_VisualEvent.cpp.obj",
			"AISenseConfig_VisualEvent.cpp.obj",
			"AISenseEvent_VisualEvent.cpp.obj",
			"AISentienceModule.cpp.obj",
			"AISpawn.cpp.obj",
			"AISquad.cpp.obj",
			"AIVisualEvent.cpp.obj",
			"AIVoiceLines.cpp.obj",
			"BTDecorator_IsCoverEffective.cpp.obj",
			"BTDecorator_ViableAttackExists.cpp.obj",
			"BTService_LockTarget.cpp.obj",
			"BTService_ReleaseCover.cpp.obj",
			"BTService_UpdateCoverData.cpp.obj",
			"BTTask_CoverQuery.cpp.obj",
			"BTTask_PerformMeleeAttack.cpp.obj",
			"BTTask_PerformMeleeAttackInfallible.cpp.obj",
			"BTTask_PerformSpecificAttack.cpp.obj",
			"BTTask_PlayDialogueLine.cpp.obj",
			"BTTask_SetSAIState.cpp.obj",
			"BTTask_StopInvestigating.cpp.obj",
			"ClimbingNavLink.cpp.obj",
			"CurrentDialogue.cpp.obj",
			"Dialogue.cpp.obj",
			"DialogueComponent.cpp.obj",
			"DialogueLine.cpp.obj",
			"EnvQueryContext_ClaimedCover.cpp.obj",
			"EnvQueryTest_CoverTrace.cpp.obj",
			"SAIComponent.cpp.obj",
			"SAIController.cpp.obj",
			"SAICoverData.cpp.obj",
			"SAICoverDebugActor.cpp.obj",
			"SAICoverDebugPrimitiveComponent.cpp.obj",
			"SAICoverGenerationSettings.cpp.obj",
			"SAICoverGenerationSubsystem.cpp.obj",
			"SAICoverPoint.cpp.obj",
			"SAICoverPointOctreeElement.cpp.obj",
			"SAICoverSubsystem.cpp.obj",
			"SAIEnvQueryItemType_Cover.cpp.obj",
			"SAIEnvQueryTest_RelativePosition.cpp.obj",
			"SAIEQSGen_CoverPoints.cpp.obj",
			"SAIEQSGen_NavmeshEdges.cpp.obj",
			"SAIEQSTest_CoverFiringOptions.cpp.obj",
			"SAIEQSTest_LimitDistanceOffset.cpp.obj",
			"SAIEQSTest_LineLimitedDistance.cpp.obj",
			"SAIEQSTestingPawn.cpp.obj",
			"SAIInterestPoint.cpp.obj",
			"SAIManager.cpp.obj",
			"SAIMapInteraction.cpp.obj",
			"SAIMeleeComponent.cpp.obj",
			"SAINavBlockingVolume.cpp.obj",
			"SAINavigationSystem.cpp.obj",
			"SAINavMesh.cpp.obj",
			"SAIPathFollowingComponent.cpp.obj",
			"SAIPatrol_NEW.cpp.obj",
			"SAIPatrolPath.cpp.obj",
			"SAIPatrolPoint.cpp.obj",
			"SAIPerception.cpp.obj",
			"SAIPerceptionComponent.cpp.obj",
			"SAIPointOfInterest.cpp.obj",
			"SAISettings.cpp.obj",
			"SAISound.cpp.obj",
			"SAISpawner.cpp.obj",
			"SAISquad.cpp.obj",
			"SAISquadComponent.cpp.obj",
			"SAISquadInfo.cpp.obj",
			"SAISubsystem.cpp.obj",
			"SAITarget.cpp.obj",
			"SeenTarget.cpp.obj",
			"SplinePath.cpp.obj",
			"SplinePathFollowingComponent.cpp.obj",
			"SquadMemberInfo.cpp.obj",
			"SquadSpawner.cpp.obj",
			"TeamAttitude.cpp.obj"
		],
		"Module.AISentience.gen.1_of_4.cpp.obj": [
			"AIHeard.gen.cpp.obj",
			"AIInfoSharer.gen.cpp.obj",
			"AIInfoSharingComponent.gen.cpp.obj",
			"AIInteractionAnimations.gen.cpp.obj",
			"AISense_VisualEvent.gen.cpp.obj",
			"AISenseConfig_VisualEvent.gen.cpp.obj",
			"AISenseEvent_VisualEvent.gen.cpp.obj",
			"AISentience.init.gen.cpp.obj",
			"AISpawn.gen.cpp.obj",
			"AISquad.gen.cpp.obj",
			"AIVisualEvent.gen.cpp.obj",
			"AIVoiceLines.gen.cpp.obj",
			"BTDecorator_IsCoverEffective.gen.cpp.obj",
			"BTDecorator_ViableAttackExists.gen.cpp.obj",
			"BTService_LockTarget.gen.cpp.obj",
			"BTService_ReleaseCover.gen.cpp.obj",
			"BTService_UpdateCoverData.gen.cpp.obj",
			"BTTask_CoverQuery.gen.cpp.obj",
			"BTTask_PerformMeleeAttack.gen.cpp.obj",
			"BTTask_PerformMeleeAttackInfallible.gen.cpp.obj",
			"BTTask_PerformSpecificAttack.gen.cpp.obj",
			"BTTask_PlayDialogueLine.gen.cpp.obj",
			"BTTask_SetSAIState.gen.cpp.obj",
			"BTTask_StopInvestigating.gen.cpp.obj",
			"ChangedSquadMCDelegateDelegate.gen.cpp.obj",
			"Climber.gen.cpp.obj",
			"ClimbingNavLink.gen.cpp.obj",
			"CurrentDialogue.gen.cpp.obj",
			"Dialogue.gen.cpp.obj",
			"DialogueComponent.gen.cpp.obj"
		],
		"Module.AISentience.gen.2_of_4.cpp.obj": [
			"DialogueLine.gen.cpp.obj",
			"DialogueUser.gen.cpp.obj",
			"EClimbingType.gen.cpp.obj",
			"ECoverFiringOptions.gen.cpp.obj",
			"EDialoguePriorityType.gen.cpp.obj",
			"EDialogueType.gen.cpp.obj",
			"EMoraleLevelType.gen.cpp.obj",
			"EnvQueryContext_ClaimedCover.gen.cpp.obj",
			"EPatrolType.gen.cpp.obj",
			"ERelativeType.gen.cpp.obj",
			"ESAIBehaviors_Calm.gen.cpp.obj",
			"ESAIBehaviors_Combat.gen.cpp.obj",
			"ESAISoundType.gen.cpp.obj",
			"ESAISquad_Types.gen.cpp.obj",
			"ESAIState.gen.cpp.obj",
			"ESAITeam.gen.cpp.obj",
			"EStaggerDirection.gen.cpp.obj",
			"NavmeshTilesUpdatedDelegate.gen.cpp.obj",
			"SAIComponent.gen.cpp.obj",
			"SAIController.gen.cpp.obj"
		],
		"Module.AISentience.gen.3_of_4.cpp.obj": [
			"SAICoverData.gen.cpp.obj",
			"SAICoverDebugActor.gen.cpp.obj",
			"SAICoverDebugPrimitiveComponent.gen.cpp.obj",
			"SAICoverGenerationSettings.gen.cpp.obj",
			"SAICoverGenerationSubsystem.gen.cpp.obj",
			"SAICoverPoint.gen.cpp.obj",
			"SAICoverPointOctreeElement.gen.cpp.obj",
			"SAICoverSubsystem.gen.cpp.obj",
			"SAIEnvQueryItemType_Cover.gen.cpp.obj",
			"SAIEnvQueryTest_RelativePosition.gen.cpp.obj",
			"SAIEQSGen_CoverPoints.gen.cpp.obj",
			"SAIEQSGen_NavmeshEdges.gen.cpp.obj",
			"SAIEQSTest_CoverFiringOptions.gen.cpp.obj",
			"SAIEQSTest_LimitDistanceOffset.gen.cpp.obj",
			"SAIEQSTest_LineLimitedDistance.gen.cpp.obj",
			"SAIEQSTestingPawn.gen.cpp.obj",
			"SAIInterestPoint.gen.cpp.obj",
			"SAIManager.gen.cpp.obj",
			"SAIMapInteraction.gen.cpp.obj",
			"SAIMeleeComponent.gen.cpp.obj",
			"SAINavBlockingVolume.gen.cpp.obj",
			"SAINavigationSystem.gen.cpp.obj",
			"SAINavMesh.gen.cpp.obj",
			"SAIPathFollowingComponent.gen.cpp.obj",
			"SAIPatrol_NEW.gen.cpp.obj",
			"SAIPatrolPath.gen.cpp.obj",
			"SAIPatrolPoint.gen.cpp.obj",
			"SAIPerception.gen.cpp.obj",
			"SAIPerceptionComponent.gen.cpp.obj",
			"SAIPointOfInterest.gen.cpp.obj",
			"SAISettings.gen.cpp.obj",
			"SAISound.gen.cpp.obj"
		],
		"Module.AISentience.gen.4_of_4.cpp.obj": [
			"SAISpawner.gen.cpp.obj",
			"SAISquad.gen.cpp.obj",
			"SAISquadComponent.gen.cpp.obj",
			"SAISquadInfo.gen.cpp.obj",
			"SAISquadMemberInterface.gen.cpp.obj",
			"SAISubsystem.gen.cpp.obj",
			"SAITarget.gen.cpp.obj",
			"SAITargetSightUpdatedDelegateDelegate.gen.cpp.obj",
			"SAITargetUpdatedDelegateDelegate.gen.cpp.obj",
			"SeenTarget.gen.cpp.obj",
			"ShareInfoMCDelegateDelegate.gen.cpp.obj",
			"SplinePath.gen.cpp.obj",
			"SplinePathFollowingComponent.gen.cpp.obj",
			"SquadMemberInfo.gen.cpp.obj",
			"SquadSpawner.gen.cpp.obj",
			"TeamAttitude.gen.cpp.obj"
		]
	}
}